basket-viz/__init__.py
basket-viz/shot_charts/__init__.py
basket-viz/shot_charts/visualize.py
basket_viz/__init__.py
basket_viz/config/__init__.py
basket_viz/config/euroleague_color_config.py
basket_viz/court/__init__.py
basket_viz/court/euroleague_team_configs.py
basket_viz/court/shot_charts.py
basket_viz/export_util/__init__.py
basket_viz/export_util/fig_export.py
basket_viz/img_util/__init__.py
basket_viz/img_util/img_patcher.py
basket_viz/img_util/img_processor.py
basket_viz/overlay/__init__.py
basket_viz/overlay/score_trajectory.py
basket_viz/radar/__init__.py
basket_viz/radar/standard.py
basket_viz/relationships/__init__.py
basket_viz/relationships/plotter.py
basket_viz/relationships/plotter_v2.py
basket_viz/relationships/team_configs.py
basket_viz/shot_charts/__init__.py
basket_viz/shot_charts/scatter.py
basket_viz-0.2.2.dist-info/licenses/LICENSE
basket_viz-0.2.2.dist-info/METADATA
basket_viz-0.2.2.dist-info/WHEEL
basket_viz-0.2.2.dist-info/top_level.txt
basket_viz-0.2.2.dist-info/RECORD
