Metadata-Version: 2.4
Name: basket_viz
Version: 0.2.2
Summary: A Python library for creating interactive and customizable visualizations of basketball statistics.
Home-page: https://github.com/sVujke/basket-viz
Author: basket-viz
Author-email: basketviz@gmail.com
License: MIT
Classifier: Development Status :: 2 - Pre-Alpha
Classifier: Intended Audience :: Developers
Classifier: Intended Audience :: Science/Research
Classifier: Topic :: Scientific/Engineering :: Visualization
Classifier: Topic :: Software Development :: Libraries :: Python Modules
Classifier: License :: OSI Approved :: MIT License
Classifier: Programming Language :: Python :: 3
Classifier: Programming Language :: Python :: 3.6
Classifier: Programming Language :: Python :: 3.7
Classifier: Programming Language :: Python :: 3.8
Classifier: Programming Language :: Python :: 3.9
Classifier: Operating System :: OS Independent
Requires-Python: >=3.8
License-File: LICENSE
Requires-Dist: click
Requires-Dist: Sphinx
Requires-Dist: coverage
Requires-Dist: flake8
Requires-Dist: python-dotenv>=0.5.1
Requires-Dist: matplotlib==3.7.1
Requires-Dist: pandas==2.0.3
Requires-Dist: Pillow==9.5.0
Requires-Dist: requests==2.26.0
Requires-Dist: numpy==1.21.0
Dynamic: author
Dynamic: author-email
Dynamic: classifier
Dynamic: description
Dynamic: description-content-type
Dynamic: home-page
Dynamic: license
Dynamic: license-file
Dynamic: requires-dist
Dynamic: requires-python
Dynamic: summary
